{
  "8b078c7afe41e54391e32a39f33d2f35": {
    "id": "8b078c7afe41e54391e32a39f33d2f35",
    "path": "/Users/joshkennedy00/sites/joshs/sandbox/content/brain/JSDoc-plus-Typescript/index.md",
    "tokens": {
      "title": 1,
      "jsdoc": 3,
      "typescript": 5,
      "vscode": 4,
      "match": 1,
      "made": 1,
      "heaven": 1,
      "date": 1,
      "20210310t151713467z": 1,
      "tags": 1,
      "js": 1,
      "documentation": 1,
      "make": 1,
      "coolest": 1,
      "tool": 5,
      "tips": 2,
      "below": 1,
      "screenshot": 1,
      "tip": 3,
      "function": 10,
      "wrote": 2,
      "explains": 2,
      "perfectly": 2,
      "what": 3,
      "does": 2,
      "ill": 1,
      "never": 1,
      "look": 1,
      "back": 1,
      "remember": 1,
      "how": 3,
      "use": 3,
      "functiondefinetypefunctiontooltippng": 1,
      "typing": 1,
      "out": 1,
      "params": 1,
      "return": 4,
      "type": 8,
      "get": 1,
      "safety": 1,
      "ts": 2,
      "compiler": 1,
      "also": 1,
      "definitions": 1,
      "ahhhmazing": 1,
      "combine": 1,
      "short": 1,
      "description": 1,
      "beautiful": 1,
      "well": 1,
      "documented": 1,
      "very": 1,
      "little": 1,
      "work": 1,
      "here": 1,
      "example": 1,
      "produced": 1,
      "above": 1,
      "returns": 1,
      "string": 1,
      "name": 1,
      "data": 4,
      "passed": 1,
      "param": 1,
      "value": 2,
      "getting": 1,
      "definition": 1,
      "export": 1,
      "definetypedata": 1,
      "tjsonvalue": 1,
      "jsonvaluetypesasstrings": 1,
      "const": 1,
      "primitive": 6,
      "typeof": 1,
      "if": 6,
      "arrayisarraydata": 1,
      "array": 1,
      "null": 2,
      "throw": 4,
      "new": 4,
      "typeerrornot": 3,
      "valid": 3,
      "json": 3,
      "sorry": 3,
      "symbol": 1,
      "bigint": 1,
      "undefined": 1,
      "typeerrorno": 1,
      "given": 1
    },
    "content": "---\ntitle: JSDoc + Typescript + VScode = Match Mad",
    "heading": "JSDoc + Typescript + VScode = Match Made in Heaven"
  },
  "5a6a3e0b0afc1b0678559d7806e19dfe": {
    "id": "5a6a3e0b0afc1b0678559d7806e19dfe",
    "path": "/Users/joshkennedy00/sites/joshs/sandbox/content/brain/Php-JSON-body/index.mdx",
    "tokens": {
      "20200726": 1,
      "title": 1,
      "get": 2,
      "request": 3,
      "body": 2,
      "json": 4,
      "php": 4,
      "tags": 1,
      "api": 1,
      "date": 1,
      "filegetcontentsphpinput": 1,
      "data": 2,
      "jsondecodejson": 1,
      "variable": 1,
      "will": 1,
      "contain": 1
    },
    "content": "---\ntitle: Get The Request Body of JSON in PHP\ntag",
    "heading": "Get The Request Body of JSON in PHP"
  },
  "8273500e445cde26c08413e456b07995": {
    "id": "8273500e445cde26c08413e456b07995",
    "path": "/Users/joshkennedy00/sites/joshs/sandbox/content/brain/WPRedirect/index.mdx",
    "tokens": {
      "2": 2,
      "365": 1,
      "86400": 1,
      "20200811": 1,
      "title": 1,
      "how": 1,
      "quick": 1,
      "easy": 1,
      "redirect": 2,
      "wordpress": 1,
      "cookies": 2,
      "date": 1,
      "tags": 1,
      "php": 2,
      "wp": 1,
      "super": 1,
      "simple": 1,
      "snippet": 1,
      "redirects": 1,
      "user": 2,
      "gives": 1,
      "them": 1,
      "cookie": 1,
      "only": 1,
      "happens": 1,
      "once": 1,
      "per": 1,
      "addaction": 1,
      "templateredirect": 1,
      "function": 1,
      "if": 1,
      "isfrontpage": 1,
      "issetcookieseensplashpage": 1,
      "setcookieseensplashpage": 1,
      "true": 1,
      "time": 1,
      "years": 1,
      "wpredirect": 1,
      "homeurl": 1,
      "wpadmin": 1,
      "die": 1
    },
    "content": "---\ntitle: How to Quick and Easy Redirect In Wordp",
    "heading": "How to Quick and Easy Redirect In Wordpress With Cookies"
  },
  "666bc815ebebe55935bb5672e7444766": {
    "id": "666bc815ebebe55935bb5672e7444766",
    "path": "/Users/joshkennedy00/sites/joshs/sandbox/content/brain/adding-fields-to-gatsby-schema/index.md",
    "tokens": {
      "title": 4,
      "adding": 1,
      "customizing": 2,
      "gatsby": 7,
      "graphql": 5,
      "schema": 6,
      "date": 1,
      "20200901t181058268z": 1,
      "tags": 1,
      "more": 3,
      "depth": 1,
      "information": 3,
      "go": 1,
      "docs": 1,
      "customizationhttpswwwgatsbyjscomdocsschemacustomization": 1,
      "there": 4,
      "bunch": 2,
      "ways": 3,
      "edit": 1,
      "add": 7,
      "two": 1,
      "found": 3,
      "easiest": 2,
      "using": 2,
      "createresolvers": 4,
      "api": 6,
      "oncreatenode": 2,
      "createnodefield": 4,
      "function": 3,
      "fields": 9,
      "existing": 1,
      "nodes": 4,
      "depending": 1,
      "where": 1,
      "how": 1,
      "pulled": 1,
      "depicts": 1,
      "which": 3,
      "use": 4,
      "third": 2,
      "party": 2,
      "if": 6,
      "created": 4,
      "github": 1,
      "then": 3,
      "our": 6,
      "options": 2,
      "smaller": 1,
      "lives": 2,
      "little": 1,
      "harder": 1,
      "way": 3,
      "type": 5,
      "all": 3,
      "need": 1,
      "create": 1,
      "object": 3,
      "keys": 1,
      "types": 1,
      "wish": 1,
      "change": 2,
      "resolvers": 4,
      "will": 4,
      "js": 3,
      "exportscreateresolvers": 1,
      "const": 4,
      "githubgist": 1,
      "description": 2,
      "resolve": 2,
      "source": 2,
      "args": 2,
      "context": 3,
      "info": 2,
      "return": 3,
      "sourcedescription": 1,
      "sourcedescriptiontolowercase": 1,
      "string": 1,
      "sourcefiles0name": 1,
      "createresolversresolvers": 1,
      "lowercase": 1,
      "sure": 1,
      "why": 1,
      "would": 1,
      "want": 1,
      "property": 2,
      "gist": 1,
      "based": 1,
      "first": 1,
      "file": 1,
      "name": 2,
      "one": 2,
      "thing": 1,
      "note": 2,
      "order": 1,
      "able": 2,
      "used": 2,
      "pull": 1,
      "filesname": 1,
      "because": 1,
      "dont": 1,
      "wont": 1,
      "resolver": 2,
      "internaltype": 1,
      "made": 1,
      "much": 1,
      "easier": 1,
      "can": 3,
      "method": 2,
      "mentioned": 1,
      "above": 1,
      "even": 1,
      "around": 1,
      "having": 1,
      "query": 1,
      "custom": 1,
      "frontmatter": 1,
      "author": 1,
      "resolvesource": 1,
      "contextnodemodelgetnodebyid": 1,
      "id": 1,
      "sourceauthor": 1,
      "authorjson": 1,
      "createresolversresolver": 1,
      "parameter": 1,
      "some": 1,
      "methods": 1,
      "attached": 1,
      "allows": 1,
      "run": 2,
      "queries": 1,
      "here": 1,
      "accessing": 1,
      "gatsbys": 1,
      "data": 1,
      "store": 1,
      "field": 1,
      "resolvershttpswwwgatsbyjscomdocsschemacustomizationaccessinggatsbysdatastorefromfieldresolvers": 1,
      "while": 1,
      "certainly": 1,
      "works": 1,
      "simpler": 1,
      "least": 1,
      "think": 1,
      "runs": 1,
      "when": 1,
      "new": 1,
      "node": 6,
      "exportsoncreatenode": 1,
      "actions": 2,
      "getnode": 2,
      "nodeinternaltype": 1,
      "mdx": 1,
      "value": 2,
      "createfilepath": 1,
      "slug": 1,
      "basically": 1,
      "check": 1,
      "see": 1,
      "correct": 1,
      "give": 1,
      "caveat": 1,
      "under": 1,
      "biggest": 1,
      "deal": 1,
      "something": 1,
      "thats": 1,
      "docshttpswwwgatsbyjscomdocs": 1,
      "also": 1,
      "jason": 1,
      "lengstorf": 1,
      "videoshttpswwwyoutubecomplaylistlistplz8izfnkeqljd3bxecwhcpmfaada4te": 1
    },
    "content": "---\ntitle: Adding and Customizing Gatsby Graphql S",
    "heading": "Adding and Customizing Gatsby Graphql Schema"
  },
  "64207c172a339b54a32369b7ec8f1c22": {
    "id": "64207c172a339b54a32369b7ec8f1c22",
    "path": "/Users/joshkennedy00/sites/joshs/sandbox/content/brain/animating-shadows/index.mdx",
    "tokens": {
      "0": 6,
      "1": 1,
      "title": 1,
      "animating": 2,
      "shadows": 2,
      "date": 1,
      "20210311t145125542z": 1,
      "tags": 1,
      "css": 4,
      "animation": 4,
      "import": 1,
      "stylecss": 1,
      "web": 1,
      "can": 2,
      "tricky": 1,
      "thing": 1,
      "if": 2,
      "animate": 2,
      "wrong": 1,
      "property": 2,
      "uianimation": 1,
      "will": 1,
      "feel": 1,
      "choppy": 1,
      "janky": 2,
      "safe": 1,
      "properties": 2,
      "dont": 1,
      "cause": 1,
      "layout": 1,
      "shift": 1,
      "causing": 1,
      "entire": 1,
      "page": 2,
      "large": 1,
      "portions": 1,
      "re": 1,
      "paint": 1,
      "move": 1,
      "around": 1,
      "some": 1,
      "these": 1,
      "transform": 1,
      "opacity": 1,
      "color": 1,
      "actually": 1,
      "thats": 1,
      "pretty": 1,
      "much": 1,
      "there": 1,
      "few": 1,
      "others": 1,
      "what": 1,
      "going": 2,
      "talk": 1,
      "today": 1,
      "boxshadow": 1,
      "give": 1,
      "however": 1,
      "use": 1,
      "filter": 3,
      "function": 1,
      "dropshadow": 1,
      "get": 1,
      "those": 1,
      "silky": 1,
      "smooth": 1,
      "shadow": 1,
      "animations": 1,
      "after": 1,
      "card": 1,
      "dropshadow0": 2,
      "3px": 1,
      "rgba0": 2,
      "04": 2,
      "transition": 1,
      "all": 1,
      "02s": 1,
      "cubicbezier055": 1,
      "05": 1,
      "non": 1,
      "stuff": 1,
      "width": 1,
      "150px": 2,
      "height": 1,
      "borderradius": 1,
      "16px": 1,
      "background": 1,
      "dodgerblue": 1,
      "cardhover": 1,
      "4px": 1,
      "20px": 1,
      "div": 3,
      "classcardcontainer": 1,
      "spanhover": 1,
      "mespan": 1,
      "classcard": 1,
      "card1div": 1
    },
    "content": "---\ntitle: Animating Shadows\ndate: '2021-03-11T14:",
    "heading": "Animating Shadows"
  },
  "e7966103ce0f8d3b318a8860f051ddae": {
    "id": "e7966103ce0f8d3b318a8860f051ddae",
    "path": "/Users/joshkennedy00/sites/joshs/sandbox/content/brain/animating-shadows/style.css",
    "tokens": {
      "0": 11,
      "1": 1,
      "card": 1,
      "transition": 1,
      "all": 1,
      "02s": 1,
      "cubicbezier055": 1,
      "05": 1,
      "non": 1,
      "animation": 1,
      "stuff": 1,
      "width": 1,
      "150px": 2,
      "height": 1,
      "borderradius": 2,
      "16px": 1,
      "background": 2,
      "dodgerblue": 1,
      "margin": 1,
      "auto": 1,
      "card1": 1,
      "filter": 2,
      "dropshadow0": 2,
      "3px": 1,
      "rgba0": 2,
      "04": 2,
      "card1hover": 1,
      "4px": 2,
      "20px": 3,
      "cardcontainer": 2,
      "white": 1,
      "8px": 2,
      "boxshadow": 1,
      "rgb0": 1,
      "01": 1,
      "padding": 1,
      "marginbottom": 2,
      "span": 1,
      "fontsize": 1,
      "24px": 1,
      "display": 1,
      "block": 1,
      "textalign": 1,
      "center": 1,
      "margintop": 1,
      "5px": 1
    },
    "content": ".card {\n  transition: all 0.2s cubic-bezier(0.55, ",
    "heading": ""
  },
  "07e2337dbcfe2d65edefd1552366ae70": {
    "id": "07e2337dbcfe2d65edefd1552366ae70",
    "path": "/Users/joshkennedy00/sites/joshs/sandbox/content/brain/aspect-ratios-with-css/index.md",
    "tokens": {
      "0": 3,
      "16": 1,
      "100": 4,
      "title": 1,
      "aspect": 1,
      "ratios": 1,
      "css": 8,
      "date": 1,
      "20210305t140939534z": 1,
      "tags": 1,
      "aspectratio": 2,
      "iframes": 2,
      "sizing": 1,
      "videos": 3,
      "always": 2,
      "been": 1,
      "something": 1,
      "difficult": 1,
      "past": 1,
      "might": 1,
      "brought": 1,
      "some": 1,
      "library": 2,
      "dave": 1,
      "ruperts": 1,
      "jquery": 1,
      "plugin": 1,
      "fitvids": 2,
      "however": 2,
      "there": 1,
      "new": 2,
      "property": 2,
      "coming": 1,
      "browsers": 1,
      "already": 1,
      "implemented": 1,
      "called": 1,
      "allows": 1,
      "set": 1,
      "ratio": 4,
      "element": 1,
      "will": 1,
      "retain": 1,
      "width": 3,
      "height": 3,
      "iframe": 2,
      "width100": 1,
      "aspectratio169": 1,
      "most": 2,
      "done": 1,
      "easy": 1,
      "really": 1,
      "may": 2,
      "able": 1,
      "used": 1,
      "production": 1,
      "yet": 1,
      "without": 1,
      "fallbacks": 1,
      "if": 1,
      "need": 2,
      "fallback": 1,
      "want": 1,
      "solution": 1,
      "than": 1,
      "inserts": 1,
      "page": 1,
      "can": 1,
      "put": 1,
      "stylesheet": 1,
      "position": 2,
      "absolute": 1,
      "top": 1,
      "left": 1,
      "iframewrapper": 1,
      "relative": 1,
      "paddingtop": 1,
      "calc9": 1
    },
    "content": "---\ntitle: Aspect Ratios With CSS\ndate: '2021-03-0",
    "heading": "Aspect Ratios With CSS"
  },
  "3dcc732eebdc3284d52e8c2055613326": {
    "id": "3dcc732eebdc3284d52e8c2055613326",
    "path": "/Users/joshkennedy00/sites/joshs/sandbox/content/brain/colorful-console-logs-in-node/index.md",
    "tokens": {
      "32": 1,
      "382": 2,
      "482": 1,
      "25500": 1,
      "title": 1,
      "writing": 1,
      "colorful": 1,
      "console": 3,
      "logs": 2,
      "node": 3,
      "date": 1,
      "20210618t120521263z": 1,
      "tags": 1,
      "js": 5,
      "debugging": 1,
      "ascii": 1,
      "getting": 1,
      "stylish": 2,
      "browser": 3,
      "easy": 1,
      "fun": 1,
      "because": 1,
      "can": 6,
      "use": 4,
      "css": 2,
      "see": 2,
      "brain": 1,
      "dumpbrainfancyconsolelogs": 1,
      "how": 2,
      "consolelogs": 1,
      "ever": 1,
      "arent": 1,
      "outputting": 5,
      "understand": 1,
      "text": 12,
      "based": 1,
      "stdout": 1,
      "terminal": 2,
      "emulator": 2,
      "ansi": 1,
      "escape": 4,
      "sequences": 1,
      "here": 4,
      "example": 5,
      "what": 3,
      "lookis": 1,
      "consolelog": 4,
      "styles": 4,
      "x1b32ms": 1,
      "x1b0m": 5,
      "am": 3,
      "green": 5,
      "outputs": 4,
      "textiamgreenexamplepng": 1,
      "very": 1,
      "gross": 1,
      "readable": 1,
      "whats": 1,
      "going": 1,
      "first": 1,
      "part": 4,
      "x1b": 2,
      "sequence": 4,
      "telling": 1,
      "change": 1,
      "color": 14,
      "more": 2,
      "less": 1,
      "honest": 1,
      "im": 1,
      "exactly": 1,
      "sure": 1,
      "next": 3,
      "declare": 4,
      "apparently": 1,
      "then": 3,
      "letter": 2,
      "m": 2,
      "which": 1,
      "means": 2,
      "done": 1,
      "declaring": 2,
      "our": 7,
      "wikipedia": 3,
      "articlehttpsenwikipediaorgwikiansiescapecode": 3,
      "shows": 1,
      "full": 1,
      "list": 2,
      "codes": 2,
      "s": 2,
      "putting": 1,
      "place": 2,
      "holder": 1,
      "go": 1,
      "last": 1,
      "another": 2,
      "its": 1,
      "0m": 1,
      "reset": 1,
      "resetting": 1,
      "back": 1,
      "default": 1,
      "background": 7,
      "colors": 2,
      "also": 2,
      "set": 1,
      "looks": 2,
      "x1b32mx1b41m": 1,
      "red": 6,
      "backgroundgreentextredbackgroundpng": 1,
      "everything": 1,
      "same": 1,
      "except": 1,
      "added": 1,
      "additional": 1,
      "before": 2,
      "placeholder": 1,
      "available": 1,
      "memorizing": 1,
      "those": 1,
      "strange": 1,
      "ideal": 1,
      "some": 1,
      "emulators": 1,
      "support": 1,
      "rgb": 6,
      "makes": 1,
      "most": 1,
      "sense": 1,
      "slightly": 1,
      "different": 1,
      "syntax": 2,
      "x1b38225500ms": 1,
      "coderedtextpng": 1,
      "lets": 1,
      "break": 1,
      "down": 1,
      "start": 2,
      "off": 1,
      "familiar": 1,
      "now": 1,
      "foreground": 1,
      "values": 1,
      "separated": 1,
      "semicolons": 1,
      "finish": 1,
      "if": 2,
      "wanted": 1,
      "instead": 1,
      "x1b48225500ms": 1,
      "coderedbackgroundpng": 1,
      "there": 1,
      "other": 1,
      "things": 1,
      "style": 1,
      "make": 1,
      "bold": 1,
      "brighter": 1,
      "dimmer": 1,
      "interested": 1,
      "digging": 1,
      "good": 1
    },
    "content": "---\ntitle: Writing Colorful console logs in node\nd",
    "heading": "Writing Colorful console logs in node"
  },
  "774c81f69300212b3189ca67463d9916": {
    "id": "774c81f69300212b3189ca67463d9916",
    "path": "/Users/joshkennedy00/sites/joshs/sandbox/content/brain/copy-to-clipboard-from-commandline/index.md",
    "tokens": {
      "title": 1,
      "copy": 2,
      "clipboard": 3,
      "commandline": 1,
      "date": 1,
      "20210225t205908094z": 1,
      "tags": 1,
      "linux": 2,
      "can": 1,
      "automatically": 1,
      "using": 1,
      "pbcopy": 2,
      "zsh": 1,
      "cat": 1,
      "packagejson": 1
    },
    "content": "---\ntitle: Copy to Clipboard from Commandline\ndate",
    "heading": "Copy to Clipboard from Commandline"
  },
  "a8002bc0973e0b19431bc1e2910faf63": {
    "id": "a8002bc0973e0b19431bc1e2910faf63",
    "path": "/Users/joshkennedy00/sites/joshs/sandbox/content/brain/electron-js/index.md",
    "tokens": {
      "title": 1,
      "electron": 3,
      "js": 3,
      "tips": 2,
      "date": 1,
      "20200924t141029579z": 1,
      "tags": 1,
      "desktop": 2,
      "app": 2,
      "electronjs": 1,
      "way": 1,
      "make": 1,
      "application": 1,
      "using": 2,
      "web": 1,
      "technology": 1,
      "nodejs": 1,
      "example": 1,
      "repo": 1,
      "bbmodulegeneratorhttpsgithubcomjoshatoutthinkbbmodulegeneratorelectrongit": 1,
      "react": 3,
      "use": 1,
      "create": 1,
      "obviously": 1,
      "some": 1,
      "limitations": 1,
      "works": 1,
      "pretty": 1,
      "well": 1,
      "main": 1,
      "file": 1,
      "uses": 1,
      "will": 1,
      "need": 1,
      "live": 1,
      "public": 1,
      "wont": 1,
      "ignore": 1,
      "when": 1,
      "build": 1
    },
    "content": "---\ntitle: Electron Js Tips\ndate: '2020-09-24T14:1",
    "heading": "Electron Js Tips"
  },
  "2f7b16c13525fd154d960b83864fc003": {
    "id": "2f7b16c13525fd154d960b83864fc003",
    "path": "/Users/joshkennedy00/sites/joshs/sandbox/content/brain/execute-binaries-in-aflred-script/index.md",
    "tokens": {
      "title": 1,
      "execute": 1,
      "binaries": 2,
      "aflred": 1,
      "workflow": 3,
      "script": 3,
      "date": 1,
      "20200824t153341173z": 1,
      "tags": 1,
      "productivity": 1,
      "alfred": 3,
      "automation": 1,
      "scripts": 2,
      "when": 1,
      "want": 1,
      "write": 1,
      "use": 2,
      "command": 2,
      "line": 1,
      "commands": 1,
      "node": 2,
      "vscode": 1,
      "code": 1,
      "tell": 1,
      "exactly": 1,
      "where": 1,
      "these": 1,
      "could": 3,
      "add": 3,
      "full": 1,
      "path": 2,
      "binary": 1,
      "bash": 2,
      "usrlocalbinnode": 1,
      "somefilejs": 2,
      "create": 1,
      "environment": 2,
      "variable": 2,
      "there": 1,
      "place": 1,
      "env": 1,
      "variables": 1,
      "will": 1,
      "available": 1,
      "example": 1,
      "variablename": 1,
      "would": 1,
      "value": 1,
      "then": 1
    },
    "content": "---\ntitle: Execute Binaries In a Aflred Workflow S",
    "heading": "Execute Binaries In a Aflred Workflow Script"
  },
  "912c2cf4d054a3651b7bdacb8f29cf0c": {
    "id": "912c2cf4d054a3651b7bdacb8f29cf0c",
    "path": "/Users/joshkennedy00/sites/joshs/sandbox/content/brain/fancy-console-logs/index.md",
    "tokens": {
      "title": 1,
      "fancy": 1,
      "console": 2,
      "logs": 1,
      "date": 1,
      "20210506t134440027z": 1,
      "tags": 1,
      "js": 2,
      "debugging": 1,
      "can": 1,
      "easily": 1,
      "style": 1,
      "consolelogs": 1,
      "adding": 1,
      "c": 1,
      "beginning": 1,
      "log": 2,
      "then": 1,
      "add": 1,
      "second": 1,
      "parameter": 1,
      "function": 1,
      "string": 1,
      "containing": 1,
      "css": 1,
      "styles": 2,
      "consolelog": 1,
      "cim": 1,
      "going": 1,
      "look": 1,
      "nice": 1,
      "fontsize20px": 1,
      "background333": 1,
      "borderradius4pxpadding10px": 1,
      "example": 1,
      "logexamplepng": 1,
      "will": 1,
      "only": 1,
      "work": 1,
      "browser": 1,
      "if": 1,
      "need": 1,
      "node": 1,
      "check": 1,
      "out": 1,
      "thisbraincolorfulconsolelogsinnode": 1
    },
    "content": "---\ntitle: Fancy Console Logs\ndate: '2021-05-06T13",
    "heading": "Fancy Console Logs"
  },
  "5e58086bf642a991672ccdd1308cba61": {
    "id": "5e58086bf642a991672ccdd1308cba61",
    "path": "/Users/joshkennedy00/sites/joshs/sandbox/content/brain/fm-rust-notes/index.md",
    "tokens": {
      "0": 2,
      "1": 2,
      "4": 1,
      "5": 1,
      "8": 1,
      "22": 1,
      "32": 1,
      "1112353": 1,
      "title": 1,
      "notes": 3,
      "rust": 5,
      "frontend": 3,
      "masters": 2,
      "course": 3,
      "date": 1,
      "20210807t145352257z": 1,
      "tags": 1,
      "these": 1,
      "master": 1,
      "variables": 2,
      "let": 7,
      "mutable": 3,
      "variable": 2,
      "cant": 7,
      "even": 2,
      "mutate": 1,
      "objects": 1,
      "unlike": 2,
      "javascript": 1,
      "mut": 1,
      "varname": 3,
      "how": 3,
      "get": 3,
      "change": 4,
      "types": 1,
      "strings": 1,
      "concat": 1,
      "formatstring": 1,
      "string": 1,
      "interpolation": 1,
      "panicstring": 1,
      "println": 1,
      "var": 1,
      "var2": 1,
      "floats": 1,
      "f64": 1,
      "f32": 2,
      "ex": 1,
      "ints": 1,
      "i8": 2,
      "i16": 1,
      "i32": 1,
      "i64": 1,
      "u8": 1,
      "u16": 1,
      "no": 3,
      "decimal": 1,
      "divide": 2,
      "will": 1,
      "panic": 1,
      "also": 1,
      "char": 1,
      "its": 2,
      "valid": 1,
      "unicode": 1,
      "u32": 1,
      "booleans": 1,
      "true": 1,
      "false": 1,
      "works": 1,
      "if": 3,
      "want": 1,
      "go": 1,
      "number": 5,
      "triple": 1,
      "conditionals": 1,
      "cats": 1,
      "predicate": 1,
      "boolean": 1,
      "automatic": 1,
      "coercion": 1,
      "rs": 1,
      "x": 3,
      "expression": 4,
      "else": 1,
      "need": 1,
      "above": 1,
      "whole": 1,
      "snippet": 1,
      "statement": 3,
      "bc": 1,
      "assigning": 1,
      "coersion": 1,
      "use": 2,
      "keyword": 1,
      "numbers": 1,
      "usually": 1,
      "goes": 1,
      "small": 1,
      "big": 1,
      "functions": 3,
      "must": 1,
      "type": 3,
      "args": 1,
      "typeing": 1,
      "return": 4,
      "value": 3,
      "returntype": 1,
      "tuples": 3,
      "tuple": 2,
      "i32i32i32": 1,
      "0123": 1,
      "index": 1,
      "dot": 1,
      "notation": 1,
      "tuple1": 1,
      "unit": 2,
      "empty": 1,
      "always": 2,
      "returns": 1,
      "dont": 1,
      "dynamic": 1,
      "size": 2,
      "runtime": 1,
      "structs": 1,
      "struct": 1,
      "point": 5,
      "xi64": 1,
      "yi64": 1,
      "zi64": 1,
      "x5y6z2": 1,
      "pointx": 1,
      "add": 1,
      "new": 1,
      "fields": 1,
      "values": 1,
      "arrays": 2,
      "i323": 1,
      "js": 1,
      "length": 1,
      "inarrays": 1,
      "mix": 1,
      "iterator": 1,
      "only": 1,
      "collection": 1,
      "can": 2,
      "iterated": 1,
      "123iter": 1,
      "memory": 2,
      "list": 1,
      "bits": 2,
      "01010101110110110111011": 1,
      "array": 1,
      "bytes": 3,
      "8bits": 1,
      "doesnt": 1,
      "store": 1,
      "anything": 1,
      "elements": 1,
      "meta": 1,
      "data": 1,
      "fast": 1,
      "pattern": 1,
      "matching": 1,
      "enums": 1,
      "enum": 1,
      "poops": 1,
      "green": 1,
      "smushy": 1,
      "runny": 1,
      "now": 1,
      "mypoop": 2,
      "poopsrunny": 2,
      "smell": 1,
      "match": 1,
      "poopsgreen": 1,
      "poopssmushy": 1,
      "other": 1,
      "macros": 2,
      "code": 1,
      "transfomation": 1,
      "through": 1,
      "series": 1,
      "function": 2,
      "calls": 1,
      "compile": 1,
      "time": 1,
      "syntax": 1,
      "uses": 1,
      "signal": 1,
      "macro": 1,
      "bigger": 1,
      "more": 1,
      "precise": 1,
      "slower": 1,
      "program": 1,
      "why": 1,
      "does": 1,
      "x1": 1,
      "becuase": 1,
      "first": 1,
      "ends": 1
    },
    "content": "---\ntitle: Notes On Rust From Frontend Masters Cou",
    "heading": "Notes On Rust From Frontend Masters Course"
  },
  "5dde30c6c6d1f60ba6acb3a3760d10ab": {
    "id": "5dde30c6c6d1f60ba6acb3a3760d10ab",
    "path": "/Users/joshkennedy00/sites/joshs/sandbox/content/brain/loop-through-a-csv-php/index.md",
    "tokens": {
      "title": 1,
      "upload": 4,
      "loop": 1,
      "through": 1,
      "csv": 5,
      "file": 11,
      "php": 5,
      "date": 1,
      "20200825t152222100z": 1,
      "tags": 1,
      "files": 2,
      "read": 1,
      "tldr": 1,
      "rows": 2,
      "arraymap": 2,
      "strgetcsv": 2,
      "filescsvtmpname": 2,
      "when": 1,
      "need": 1,
      "import": 1,
      "large": 1,
      "amount": 1,
      "data": 1,
      "might": 1,
      "want": 1,
      "provide": 1,
      "ability": 1,
      "allow": 1,
      "here": 2,
      "how": 1,
      "can": 3,
      "starting": 1,
      "frontend": 1,
      "side": 1,
      "im": 1,
      "big": 1,
      "fan": 1,
      "reloading": 1,
      "whole": 1,
      "page": 2,
      "submit": 1,
      "form": 5,
      "will": 3,
      "use": 2,
      "windowfetch": 1,
      "js": 1,
      "const": 7,
      "documentqueryselector": 1,
      "if": 1,
      "return": 1,
      "button": 1,
      "formqueryselectorbutton": 1,
      "idlebuttontext": 1,
      "buttoninnertext": 2,
      "formaddeventlistenersubmit": 1,
      "sendcsvimport": 1,
      "async": 1,
      "function": 1,
      "sendcsvimporte": 1,
      "epreventdefault": 1,
      "etarget": 1,
      "loading": 1,
      "formqueryselectornamecsvfilefiles0": 1,
      "formdata": 3,
      "new": 2,
      "formdataappendcsv": 1,
      "res": 1,
      "await": 1,
      "fetch": 1,
      "url": 1,
      "method": 1,
      "post": 1,
      "credentials": 1,
      "sameorigin": 1,
      "body": 1,
      "thenres": 2,
      "resjson": 1,
      "consolelogres": 1,
      "basically": 2,
      "preventing": 1,
      "default": 1,
      "reload": 1,
      "ajax": 1,
      "then": 2,
      "creating": 1,
      "formdatahttpsdevelopermozillaorgenusdocswebapiformdataformdata": 1,
      "object": 1,
      "putting": 1,
      "type": 1,
      "input": 1,
      "send": 1,
      "right": 2,
      "over": 1,
      "wire": 1,
      "format": 1,
      "binary": 1,
      "backend": 1,
      "why": 1,
      "probably": 1,
      "what": 1,
      "going": 1,
      "get": 1,
      "contents": 1,
      "put": 1,
      "each": 2,
      "row": 2,
      "array": 2,
      "columns": 1,
      "pretty": 1,
      "easy": 1,
      "there": 1,
      "lot": 1,
      "things": 1,
      "done": 1,
      "make": 1,
      "better": 1,
      "more": 1,
      "performant": 1,
      "reading": 1,
      "stream": 1,
      "however": 1,
      "work": 1,
      "most": 1
    },
    "content": "---\ntitle: Upload and Loop Through a CSV file in p",
    "heading": "Upload and Loop Through a CSV file in php"
  },
  "8b3dfb38940f96227b11544dbcd1f03b": {
    "id": "8b3dfb38940f96227b11544dbcd1f03b",
    "path": "/Users/joshkennedy00/sites/joshs/sandbox/content/brain/parse-html-from-ajax/index.mdx",
    "tokens": {
      "20200807": 1,
      "title": 1,
      "parse": 2,
      "html": 4,
      "ajax": 1,
      "date": 1,
      "tags": 1,
      "js": 2,
      "fetch": 2,
      "how": 1,
      "only": 1,
      "peice": 1,
      "fetchabout": 1,
      "thenfunctionresponse": 1,
      "api": 1,
      "call": 1,
      "successful": 1,
      "return": 1,
      "responsetext": 1,
      "thenfunctionhtml": 1,
      "convert": 1,
      "string": 1,
      "into": 1,
      "document": 1,
      "object": 1,
      "var": 3,
      "parser": 1,
      "new": 1,
      "domparser": 1,
      "doc": 1,
      "parserparsefromstringhtml": 1,
      "texthtml": 1,
      "get": 1,
      "image": 1,
      "file": 1,
      "img": 1,
      "docqueryselectorimg": 1,
      "consolelogimg": 1,
      "catchfunctionerr": 1,
      "there": 1,
      "error": 1,
      "consolewarnsomething": 1,
      "went": 1,
      "wrong": 1,
      "err": 1,
      "taken": 1,
      "gomakethingscomhttpsgomakethingscomgettinghtmlwithfetchinvanillajs": 1
    },
    "content": "---\ntitle: Parse Html From Ajax\ndate: '2020-08-07'",
    "heading": "Parse Html From Ajax"
  },
  "e9703867d8b9f469600198ef898052ef": {
    "id": "e9703867d8b9f469600198ef898052ef",
    "path": "/Users/joshkennedy00/sites/joshs/sandbox/content/brain/proper-way-to-work-with-viewport-units/index.md",
    "tokens": {
      "1": 1,
      "100": 1,
      "title": 1,
      "proper": 1,
      "way": 1,
      "work": 1,
      "viewport": 2,
      "units": 2,
      "date": 1,
      "20210105t135024179z": 1,
      "tags": 1,
      "js": 3,
      "css": 3,
      "mobile": 1,
      "properly": 1,
      "use": 1,
      "vh": 4,
      "web": 1,
      "because": 1,
      "safari": 1,
      "some": 1,
      "thing": 1,
      "tricky": 1,
      "due": 1,
      "safaris": 1,
      "overlay": 1,
      "ui": 1,
      "first": 1,
      "add": 1,
      "get": 2,
      "height": 1,
      "multiple": 1,
      "value": 2,
      "unit": 1,
      "let": 1,
      "windowinnerheight": 1,
      "001": 1,
      "then": 2,
      "set": 1,
      "custom": 1,
      "property": 1,
      "root": 2,
      "document": 1,
      "documentdocumentelementstylesetpropertyvh": 1,
      "vhpx": 1,
      "fullheight": 1,
      "calcvarvh": 1,
      "1vh": 1,
      "code": 1,
      "came": 1,
      "csstricks": 1,
      "newsletterhttpscsstrickscomnewsletter232scrollstory": 1
    },
    "content": "---\ntitle: Proper Way To Work With Viewport Units\n",
    "heading": "Proper Way To Work With Viewport Units"
  },
  "8accbbc2d893942c19f6b85c2f814744": {
    "id": "8accbbc2d893942c19f6b85c2f814744",
    "path": "/Users/joshkennedy00/sites/joshs/sandbox/content/brain/screenWake/index.mdx",
    "tokens": {
      "0": 12,
      "1": 4,
      "2": 1,
      "50": 3,
      "100": 3,
      "103": 2,
      "200": 1,
      "20200813": 1,
      "title": 1,
      "screen": 1,
      "wake": 1,
      "lock": 1,
      "tags": 1,
      "browser": 1,
      "js": 2,
      "date": 1,
      "get": 1,
      "request": 2,
      "body": 1,
      "php": 1,
      "function": 4,
      "initdevicecaffeinemountingselector": 1,
      "const": 3,
      "mountnode": 2,
      "documentqueryselectormountingselector": 1,
      "if": 3,
      "return": 2,
      "toggleel": 1,
      "createtoggle": 2,
      "addwakelockhandlertoggleel": 1,
      "change": 1,
      "mountnodeappendchildtoggleel": 1,
      "toggle": 2,
      "documentcreateelementdiv": 1,
      "toggleclasslistaddwakelocktoggle": 1,
      "toggleinnerhtml": 1,
      "label": 3,
      "classtogglelabel": 1,
      "input": 2,
      "typecheckbox": 1,
      "name": 1,
      "id": 1,
      "classtogglecheckbox": 1,
      "div": 4,
      "classtogglewrapper": 1,
      "classtogglebgdiv": 1,
      "classtoggleswitchdiv": 1,
      "addwakelockhandlerel": 1,
      "event": 1,
      "let": 1,
      "wakelock": 2,
      "eladdeventlistenerevent": 1,
      "async": 1,
      "functione": 1,
      "etargetchecked": 2,
      "await": 1,
      "navigatorwakelockrequestscreenthenres": 1,
      "res": 1,
      "some": 1,
      "other": 1,
      "force": 1,
      "stops": 1,
      "give": 1,
      "user": 1,
      "feed": 1,
      "back": 1,
      "wakelockonrelease": 1,
      "uncheck": 1,
      "else": 1,
      "wakelockrelease": 1,
      "unchecke": 1,
      "false": 1,
      "initdevicecaffeineplacetoggle": 1,
      "css": 1,
      "wakelocktoggle": 8,
      "position": 5,
      "relative": 2,
      "display": 3,
      "inlineblock": 1,
      "fontsize": 1,
      "16px": 1,
      "boxsizing": 2,
      "borderbox": 1,
      "inherit": 2,
      "width": 5,
      "height": 5,
      "none": 2,
      "inlineflex": 1,
      "alignitems": 1,
      "center": 1,
      "inputchecked": 4,
      "togglewrapper": 5,
      "boxshadow": 3,
      "2px": 3,
      "44da60": 3,
      "toggleswitch": 2,
      "right": 2,
      "togglebg": 2,
      "border": 1,
      "1px": 2,
      "solid": 1,
      "transition": 4,
      "background": 4,
      "togglebgafter": 2,
      "transitiondelay": 2,
      "005s": 1,
      "0s": 3,
      "opacity": 3,
      "transform": 2,
      "scale0": 1,
      "marginleft": 1,
      "1em": 1,
      "2em": 3,
      "33em": 1,
      "overflow": 2,
      "visible": 1,
      "borderradius": 4,
      "25em": 2,
      "dfdfdf": 1,
      "hidden": 1,
      "absolute": 3,
      "zindex": 3,
      "transparent": 1,
      "all": 3,
      "linear": 2,
      "02s": 2,
      "transitionproperty": 1,
      "002s": 1,
      "content": 1,
      "efeff9": 1,
      "top": 1,
      "left": 1,
      "transformorigin": 1,
      "white": 1,
      "05px": 1,
      "dedede": 1,
      "calc100": 1,
      "015s": 1,
      "cubicbezier05": 1,
      "05": 1
    },
    "content": "---\ntitle: Screen Wake Lock\ntags: [browser, js]\nda",
    "heading": "Screen Wake Lock"
  },
  "56851bdc7697e3ea7d30eccd377da0c1": {
    "id": "56851bdc7697e3ea7d30eccd377da0c1",
    "path": "/Users/joshkennedy00/sites/joshs/sandbox/content/brain/scroll-timeline-animation/index.md",
    "tokens": {
      "0": 1,
      "1": 1,
      "title": 1,
      "scroll": 3,
      "timeline": 1,
      "animation": 4,
      "date": 1,
      "20210510t132308961z": 1,
      "tags": 1,
      "css": 5,
      "no": 1,
      "js": 1,
      "can": 2,
      "create": 1,
      "animations": 1,
      "based": 1,
      "position": 1,
      "theres": 1,
      "property": 2,
      "called": 1,
      "animationtimeline": 3,
      "works": 2,
      "lot": 1,
      "elementtoshow": 1,
      "1s": 2,
      "linear": 1,
      "both": 1,
      "show": 2,
      "showtimeline": 2,
      "keyframes": 1,
      "opacity": 2,
      "scrolltimeline": 1,
      "timerange": 1,
      "feature": 1,
      "still": 1,
      "really": 1,
      "experimental": 1,
      "writing": 1,
      "use": 2,
      "datahttpscaniusecomsearchanimationtimeline": 1,
      "should": 1,
      "supports": 2,
      "rule": 1,
      "guard": 1,
      "stuff": 1
    },
    "content": "---\ntitle: Scroll Timeline Animation\ndate: '2021-0",
    "heading": "Scroll Timeline Animation"
  },
  "6de98e9cec6844aa56773dbdc65b204a": {
    "id": "6de98e9cec6844aa56773dbdc65b204a",
    "path": "/Users/joshkennedy00/sites/joshs/sandbox/content/brain/simple-hmr-server/index.mdx",
    "tokens": {
      "1": 1,
      "2": 1,
      "3": 1,
      "7878": 1,
      "20210102": 1,
      "title": 1,
      "how": 1,
      "create": 2,
      "simple": 2,
      "hmr": 1,
      "server": 3,
      "date": 1,
      "tags": 1,
      "websockets": 1,
      "js": 4,
      "productivity": 1,
      "node": 2,
      "websocket": 5,
      "runs": 1,
      "fswatch": 2,
      "list": 2,
      "files": 3,
      "then": 1,
      "sends": 2,
      "message": 3,
      "client": 2,
      "causeing": 1,
      "page": 2,
      "reload": 3,
      "steps": 1,
      "include": 1,
      "script": 2,
      "markup": 1,
      "opens": 1,
      "connection": 1,
      "windowaddeventlistenerdomcontentloaded": 1,
      "function": 6,
      "const": 5,
      "ws": 3,
      "new": 2,
      "websocketwslocalhost7878": 1,
      "wsonmessage": 1,
      "functione": 1,
      "if": 3,
      "edata": 1,
      "windowlocationhref": 2,
      "install": 1,
      "library": 1,
      "npm": 1,
      "yarn": 1,
      "add": 1,
      "file": 2,
      "fs": 1,
      "requirefs": 1,
      "requirews": 1,
      "wss": 1,
      "websocketserver": 1,
      "port": 1,
      "wssonconnection": 1,
      "watchfiles": 1,
      "watchfilesws": 1,
      "fsreaddirinput": 1,
      "encoding": 2,
      "utf8": 2,
      "err": 1,
      "filesforeachfile": 1,
      "watch": 2,
      "watchfactory": 1,
      "wssendreload": 1,
      "watchinputfile": 1,
      "watchfactorycb": 1,
      "let": 1,
      "isactive": 4,
      "false": 1,
      "state": 1,
      "event": 4,
      "only": 1,
      "fires": 1,
      "once": 3,
      "return": 1,
      "filename": 3,
      "fswatchfilename": 1,
      "listener": 3,
      "cb": 1,
      "toggles": 1,
      "boolean": 1,
      "basically": 1,
      "websocketsonconnection": 1,
      "needs": 1,
      "loop": 1,
      "through": 1,
      "them": 1,
      "changed": 1,
      "fired": 1,
      "listening": 1,
      "receives": 1,
      "will": 1
    },
    "content": "---\ntitle: How to create a simple hmr server\ndate:",
    "heading": "How to create a simple hmr server"
  },
  "416394fe3eb470b066aa3f422f5ac7f1": {
    "id": "416394fe3eb470b066aa3f422f5ac7f1",
    "path": "/Users/joshkennedy00/sites/joshs/sandbox/content/brain/types-of-commits/index.md",
    "tokens": {
      "title": 1,
      "quick": 1,
      "reference": 1,
      "git": 4,
      "commit": 4,
      "types": 3,
      "date": 1,
      "20210617t131511769z": 1,
      "tags": 1,
      "having": 1,
      "defined": 1,
      "convention": 2,
      "message": 2,
      "structure": 1,
      "really": 1,
      "helpful": 1,
      "when": 1,
      "reading": 1,
      "history": 1,
      "understanding": 1,
      "what": 1,
      "pull": 1,
      "request": 1,
      "encompasses": 1,
      "popular": 2,
      "label": 2,
      "scope": 1,
      "here": 1,
      "list": 2,
      "messages": 2,
      "explanation": 1,
      "commits": 1,
      "description": 1,
      "feat": 1,
      "new": 1,
      "feature": 2,
      "being": 1,
      "added": 1,
      "particular": 1,
      "application": 1,
      "fix": 2,
      "bug": 1,
      "correlates": 1,
      "patch": 1,
      "semver": 1,
      "style": 1,
      "updates": 1,
      "related": 3,
      "styling": 1,
      "refactor": 1,
      "refactoring": 1,
      "specific": 1,
      "section": 1,
      "codebase": 1,
      "test": 1,
      "everything": 2,
      "testing": 1,
      "docs": 1,
      "documentation": 1,
      "chore": 1,
      "regular": 1,
      "code": 1,
      "maintenance": 1,
      "taken": 1,
      "blog": 1,
      "posthttpsmediumcomswlhwritingbettercommitmessages9b0b6ff60c6749fc": 1,
      "apurva": 1,
      "jain": 1,
      "which": 1,
      "goes": 1,
      "into": 1,
      "more": 1,
      "detail": 1,
      "structured": 1
    },
    "content": "---\ntitle: A quick reference of git commit types\nd",
    "heading": "A quick reference of git commit types"
  },
  "6366add706c5312ec7440920a3c5eafe": {
    "id": "6366add706c5312ec7440920a3c5eafe",
    "path": "/Users/joshkennedy00/sites/joshs/sandbox/content/brain/use-wp-cli-db/index.md",
    "tokens": {
      "title": 1,
      "using": 1,
      "wp": 4,
      "cli": 1,
      "export": 2,
      "remote": 2,
      "databases": 2,
      "date": 1,
      "20210204t170244425z": 1,
      "tags": 1,
      "mysql": 1,
      "linux": 1,
      "ssh": 1,
      "cd": 1,
      "dir": 1,
      "run": 2,
      "db": 1,
      "adddroptable": 1,
      "should": 1,
      "create": 1,
      "sql": 1,
      "file": 2,
      "copy": 1,
      "paste": 1,
      "name": 1,
      "location": 1,
      "server": 1,
      "scp": 1,
      "usernameserverlocationpathtofilesql": 1,
      "locationonlocal": 1,
      "thats": 1
    },
    "content": "---\ntitle: Using wp cli to export remote databases",
    "heading": "Using wp cli to export remote databases."
  },
  "1af3b690352fd79ca4f1a69c27fad273": {
    "id": "1af3b690352fd79ca4f1a69c27fad273",
    "path": "/Users/joshkennedy00/sites/joshs/sandbox/content/brain/vanilla-js-wp-ajax/index.mdx",
    "tokens": {
      "20200803": 1,
      "title": 1,
      "working": 1,
      "vanilla": 1,
      "js": 3,
      "wordpress": 1,
      "ajax": 2,
      "date": 1,
      "tags": 1,
      "wp": 1,
      "fetch": 2,
      "how": 1,
      "use": 1,
      "wordpresses": 1,
      "system": 1,
      "fetchwpajaxurl": 1,
      "method": 1,
      "post": 1,
      "mode": 1,
      "cors": 1,
      "credentials": 1,
      "sameorigin": 2,
      "include": 1,
      "omit": 1,
      "headers": 1,
      "contenttype": 1,
      "applicationxwwwformurlencoded": 1,
      "charsetutf8": 1,
      "body": 1,
      "toquerystringdata": 2,
      "thenres": 1,
      "consolelogres": 1,
      "function": 1,
      "const": 2,
      "urlsearhparams": 1,
      "new": 1,
      "urlsearchparamsdata": 1,
      "querystring": 2,
      "urlsearhparamstostring": 1,
      "return": 1
    },
    "content": "---\ntitle: Working with vanilla js and Wordpress a",
    "heading": "Working with vanilla js and Wordpress ajax"
  },
  "3676ce8065ad8089fd282c2cf03c553d": {
    "id": "3676ce8065ad8089fd282c2cf03c553d",
    "path": "/Users/joshkennedy00/sites/joshs/sandbox/content/brain/wp-add-style-if-shortcode/index.md",
    "tokens": {
      "100": 1,
      "title": 1,
      "add": 2,
      "style": 1,
      "if": 3,
      "shortcode": 3,
      "content": 2,
      "date": 1,
      "20210507t143811045z": 1,
      "tags": 1,
      "wp": 1,
      "shortcodes": 1,
      "snippet": 1,
      "styles": 1,
      "only": 1,
      "php": 2,
      "addactionwpenqueuescripts": 1,
      "shortcodeenqueueassets": 2,
      "function": 1,
      "global": 1,
      "post": 2,
      "isa": 1,
      "wppost": 1,
      "hasshortcode": 1,
      "postpostcontent": 1,
      "shortcodename": 1,
      "wpenqueuescriptshortcodescripts": 1,
      "themeurl": 2,
      "publicbundlejsarray": 1,
      "false": 1,
      "wpenqueuestyleshortcodestyles": 1,
      "publicbundlecssarray100": 1,
      "all": 1
    },
    "content": "---\ntitle: Add style if shortcode is in the conten",
    "heading": "Add style if shortcode is in the content"
  },
  "9d062cb867e547a39129dea9d891f9cd": {
    "id": "9d062cb867e547a39129dea9d891f9cd",
    "path": "/Users/joshkennedy00/sites/joshs/sandbox/content/brain/writing-and-executing-long-linux-commands/index.md",
    "tokens": {
      "title": 1,
      "writing": 2,
      "executing": 1,
      "long": 4,
      "linux": 4,
      "commands": 2,
      "date": 1,
      "20210315t141754751z": 1,
      "tags": 1,
      "bash": 1,
      "some": 1,
      "times": 1,
      "need": 1,
      "write": 3,
      "complicated": 1,
      "command": 10,
      "script": 3,
      "may": 1,
      "worth": 1,
      "whole": 1,
      "executable": 1,
      "its": 1,
      "too": 1,
      "terminal": 2,
      "gives": 1,
      "way": 1,
      "text": 3,
      "editor": 3,
      "then": 2,
      "save": 2,
      "execute": 2,
      "ctrl": 1,
      "x": 1,
      "e": 1,
      "hitting": 1,
      "above": 1,
      "shortcut": 1,
      "will": 5,
      "open": 2,
      "up": 1,
      "vim": 1,
      "default": 1,
      "allow": 2,
      "type": 1,
      "editing": 1,
      "after": 2,
      "execution": 1,
      "if": 1,
      "wrote": 1,
      "had": 1,
      "typo": 1,
      "can": 1,
      "run": 2,
      "fc": 1,
      "last": 1,
      "executed": 1,
      "edit": 1,
      "saving": 1,
      "again": 1
    },
    "content": "---\ntitle: writing and executing long linux comman",
    "heading": "writing and executing long linux commands"
  },
  "411d3cf3909c00ceaec30f8a1466e3e7": {
    "id": "411d3cf3909c00ceaec30f8a1466e3e7",
    "path": "/Users/joshkennedy00/sites/joshs/sandbox/content/brain/zustand-and-immerjs/index.md",
    "tokens": {
      "0": 2,
      "1": 2,
      "2": 1,
      "3": 1,
      "title": 1,
      "zustand": 4,
      "immerjs": 4,
      "creates": 1,
      "great": 3,
      "state": 4,
      "management": 4,
      "library": 2,
      "date": 1,
      "20200924t143029510z": 1,
      "tags": 1,
      "react": 5,
      "statemanagement": 1,
      "zustandhttpsgithubcompmndrszustand": 1,
      "primarily": 1,
      "used": 1,
      "although": 1,
      "can": 1,
      "use": 3,
      "vanilla": 1,
      "js": 5,
      "makes": 2,
      "really": 3,
      "simple": 3,
      "global": 1,
      "store": 1,
      "dont": 1,
      "wrap": 1,
      "app": 1,
      "context": 1,
      "flexible": 1,
      "import": 4,
      "create": 2,
      "const": 6,
      "usestore": 2,
      "createset": 2,
      "bears": 3,
      "increasepopulation": 1,
      "setstate": 2,
      "statebears": 1,
      "removeallbears": 1,
      "set": 3,
      "making": 1,
      "immutable": 3,
      "code": 4,
      "easy": 3,
      "immerjshttpsimmerjsgithubioimmerdocsintroduction": 1,
      "allows": 2,
      "work": 1,
      "way": 1,
      "mutable": 2,
      "patterns": 1,
      "apush4": 1,
      "pattern": 1,
      "mutating": 1,
      "variable": 1,
      "general": 1,
      "practice": 1,
      "very": 1,
      "readable": 1,
      "us": 1,
      "write": 1,
      "while": 1,
      "maintaining": 1,
      "safety": 1,
      "produce": 2,
      "immer": 3,
      "basestate": 1,
      "todo": 3,
      "learn": 1,
      "typescript": 1,
      "done": 2,
      "true": 2,
      "try": 1,
      "false": 1,
      "nextstate": 1,
      "producebasestate": 1,
      "draftstate": 1,
      "draftstatepush": 1,
      "tweet": 1,
      "draftstate1done": 1,
      "combining": 1,
      "these": 1,
      "two": 1,
      "libraries": 1,
      "experience": 1,
      "lush": 1,
      "forrest": 1,
      "contains": 1,
      "bear": 1,
      "fn": 1,
      "setproducefn": 1,
      "usestorestate": 1,
      "stateset": 1,
      "statelushforrestcontains": 1,
      "null": 1
    },
    "content": "---\ntitle: Zustand + Immerjs creates a great state",
    "heading": "Zustand + Immerjs creates a great state management library"
  }
}